[
  {
    "id": "3131359460",
    "lat": 48.44063186645508,
    "lon": -123.3702392578125,
    "speed": 0.0,
    "route": "70-VIC",
    "capacity": 0,
    "trip_id": "11241687:10008595:10795825",
    "stop_id": "900000",
    "bearing": 0.0,
    "timestamp": "2025-11-19T12:27:29.937375"
  },
  {
    "id": "3131359503",
    "lat": 48.44520568847656,
    "lon": -123.51908874511719,
    "speed": 0.0,
    "route": "95-VIC",
    "capacity": 0,
    "trip_id": "11242601:10032755:10049734",
    "stop_id": "102211",
    "bearing": 0.0,
    "timestamp": "2025-11-19T12:27:29.937394"
  },
  {
    "id": "3131354201",
    "lat": 48.445316314697266,
    "lon": -123.52005767822266,
    "speed": 0.0,
    "route": "81-VIC",
    "capacity": 0,
    "trip_id": "11241714:10027332:10049845",
    "stop_id": "930000",
    "bearing": 0.0,
    "timestamp": "2025-11-19T12:27:29.937400"
  },
  {
    "id": "3131351172",
    "lat": 48.44517135620117,
    "lon": -123.51868438720703,
    "speed": 0.0,
    "route": "61-VIC",
    "capacity": 0,
    "trip_id": "11242599:10043692:10049811",
    "stop_id": "930000",
    "bearing": 0.0,
    "timestamp": "2025-11-19T12:27:29.937406"
  }
]