[
  {
    "trip_id": "11343201:11434206:12155016",
    "route_id": "6-VIC",
    "start_time": "26:49:00",
    "stop_id": "100042",
    "delay": 0,
    "stop_sequence": 1,
    "time": 0
  },
  {
    "trip_id": "11343201:11434206:12155016",
    "route_id": "6-VIC",
    "start_time": "26:49:00",
    "stop_id": "100033",
    "delay": 0,
    "stop_sequence": 2,
    "time": 1769338200
  },
  {
    "trip_id": "11343201:11434206:12155016",
    "route_id": "6-VIC",
    "start_time": "26:49:00",
    "stop_id": "100045",
    "delay": 50,
    "stop_sequence": 3,
    "time": 1769338250
  },
  {
    "trip_id": "11343201:11434206:12155016",
    "route_id": "6-VIC",
    "start_time": "26:49:00",
    "stop_id": "100069",
    "delay": 50,
    "stop_sequence": 4,
    "time": 1769338310
  },
  {
    "trip_id": "11343201:11434206:12155016",
    "route_id": "6-VIC",
    "start_time": "26:49:00",
    "stop_id": "100085",
    "delay": 50,
    "stop_sequence": 5,
    "time": 1769338370
  },
  {
    "trip_id": "11343201:11434206:12155016",
    "route_id": "6-VIC",
    "start_time": "26:49:00",
    "stop_id": "100118",
    "delay": 50,
    "stop_sequence": 6,
    "time": 1769338370
  },
  {
    "trip_id": "11343201:11434206:12155016",
    "route_id": "6-VIC",
    "start_time": "26:49:00",
    "stop_id": "100133",
    "delay": 50,
    "stop_sequence": 7,
    "time": 1769338430
  },
  {
    "trip_id": "11343201:11434206:12155016",
    "route_id": "6-VIC",
    "start_time": "26:49:00",
    "stop_id": "100147",
    "delay": 50,
    "stop_sequence": 8,
    "time": 1769338430
  },
  {
    "trip_id": "11343201:11434206:12155016",
    "route_id": "6-VIC",
    "start_time": "26:49:00",
    "stop_id": "100171",
    "delay": 50,
    "stop_sequence": 9,
    "time": 1769338490
  },
  {
    "trip_id": "11343201:11434206:12155016",
    "route_id": "6-VIC",
    "start_time": "26:49:00",
    "stop_id": "100208",
    "delay": 50,
    "stop_sequence": 10,
    "time": 1769338550
  },
  {
    "trip_id": "11343201:11434206:12155016",
    "route_id": "6-VIC",
    "start_time": "26:49:00",
    "stop_id": "100234",
    "delay": 50,
    "stop_sequence": 11,
    "time": 1769338550
  },
  {
    "trip_id": "11343201:11434206:12155016",
    "route_id": "6-VIC",
    "start_time": "26:49:00",
    "stop_id": "100271",
    "delay": 50,
    "stop_sequence": 12,
    "time": 1769338610
  },
  {
    "trip_id": "11343201:11434206:12155016",
    "route_id": "6-VIC",
    "start_time": "26:49:00",
    "stop_id": "100315",
    "delay": 50,
    "stop_sequence": 13,
    "time": 1769338610
  },
  {
    "trip_id": "11343201:11434206:12155016",
    "route_id": "6-VIC",
    "start_time": "26:49:00",
    "stop_id": "100344",
    "delay": 50,
    "stop_sequence": 14,
    "time": 1769338670
  },
  {
    "trip_id": "11343201:11434206:12155016",
    "route_id": "6-VIC",
    "start_time": "26:49:00",
    "stop_id": "100401",
    "delay": 50,
    "stop_sequence": 15,
    "time": 1769338670
  },
  {
    "trip_id": "11343201:11434206:12155016",
    "route_id": "6-VIC",
    "start_time": "26:49:00",
    "stop_id": "100455",
    "delay": 50,
    "stop_sequence": 16,
    "time": 1769338730
  },
  {
    "trip_id": "11343201:11434206:12155016",
    "route_id": "6-VIC",
    "start_time": "26:49:00",
    "stop_id": "100540",
    "delay": 50,
    "stop_sequence": 17,
    "time": 1769338730
  },
  {
    "trip_id": "11343201:11434206:12155016",
    "route_id": "6-VIC",
    "start_time": "26:49:00",
    "stop_id": "100599",
    "delay": 50,
    "stop_sequence": 18,
    "time": 1769338790
  },
  {
    "trip_id": "11343201:11434206:12155016",
    "route_id": "6-VIC",
    "start_time": "26:49:00",
    "stop_id": "100655",
    "delay": 50,
    "stop_sequence": 19,
    "time": 1769338850
  },
  {
    "trip_id": "11343201:11434206:12155016",
    "route_id": "6-VIC",
    "start_time": "26:49:00",
    "stop_id": "100746",
    "delay": 50,
    "stop_sequence": 20,
    "time": 1769338850
  },
  {
    "trip_id": "11343201:11434206:12155016",
    "route_id": "6-VIC",
    "start_time": "26:49:00",
    "stop_id": "100782",
    "delay": 50,
    "stop_sequence": 21,
    "time": 1769338910
  },
  {
    "trip_id": "11343201:11434206:12155016",
    "route_id": "6-VIC",
    "start_time": "26:49:00",
    "stop_id": "100853",
    "delay": 50,
    "stop_sequence": 22,
    "time": 1769338970
  },
  {
    "trip_id": "11343201:11434206:12155016",
    "route_id": "6-VIC",
    "start_time": "26:49:00",
    "stop_id": "100895",
    "delay": 50,
    "stop_sequence": 23,
    "time": 1769338970
  },
  {
    "trip_id": "11343201:11434206:12155016",
    "route_id": "6-VIC",
    "start_time": "26:49:00",
    "stop_id": "100923",
    "delay": 50,
    "stop_sequence": 24,
    "time": 1769339030
  },
  {
    "trip_id": "11343201:11434206:12155016",
    "route_id": "6-VIC",
    "start_time": "26:49:00",
    "stop_id": "100977",
    "delay": 50,
    "stop_sequence": 25,
    "time": 1769339090
  },
  {
    "trip_id": "11343201:11434206:12155016",
    "route_id": "6-VIC",
    "start_time": "26:49:00",
    "stop_id": "101004",
    "delay": 50,
    "stop_sequence": 26,
    "time": 1769339090
  },
  {
    "trip_id": "11343201:11434206:12155016",
    "route_id": "6-VIC",
    "start_time": "26:49:00",
    "stop_id": "101034",
    "delay": 50,
    "stop_sequence": 27,
    "time": 1769339150
  },
  {
    "trip_id": "11343201:11434206:12155016",
    "route_id": "6-VIC",
    "start_time": "26:49:00",
    "stop_id": "101089",
    "delay": 50,
    "stop_sequence": 28,
    "time": 1769339150
  },
  {
    "trip_id": "11343201:11434206:12155016",
    "route_id": "6-VIC",
    "start_time": "26:49:00",
    "stop_id": "101146",
    "delay": 50,
    "stop_sequence": 29,
    "time": 1769339210
  },
  {
    "trip_id": "11343201:11434206:12155016",
    "route_id": "6-VIC",
    "start_time": "26:49:00",
    "stop_id": "101166",
    "delay": 50,
    "stop_sequence": 30,
    "time": 1769339210
  },
  {
    "trip_id": "11343201:11434206:12155016",
    "route_id": "6-VIC",
    "start_time": "26:49:00",
    "stop_id": "101257",
    "delay": 50,
    "stop_sequence": 31,
    "time": 1769339270
  },
  {
    "trip_id": "11343201:11434206:12155016",
    "route_id": "6-VIC",
    "start_time": "26:49:00",
    "stop_id": "101316",
    "delay": 50,
    "stop_sequence": 32,
    "time": 1769339330
  },
  {
    "trip_id": "11343201:11434206:12155016",
    "route_id": "6-VIC",
    "start_time": "26:49:00",
    "stop_id": "101345",
    "delay": 50,
    "stop_sequence": 33,
    "time": 1769339330
  },
  {
    "trip_id": "11343201:11434206:12155016",
    "route_id": "6-VIC",
    "start_time": "26:49:00",
    "stop_id": "101399",
    "delay": 50,
    "stop_sequence": 34,
    "time": 1769339390
  },
  {
    "trip_id": "11343201:11434206:12155016",
    "route_id": "6-VIC",
    "start_time": "26:49:00",
    "stop_id": "101412",
    "delay": 50,
    "stop_sequence": 35,
    "time": 1769339450
  },
  {
    "trip_id": "11343201:11434206:12155016",
    "route_id": "6-VIC",
    "start_time": "26:49:00",
    "stop_id": "102490",
    "delay": 0,
    "stop_sequence": 36,
    "time": 1769339510
  },
  {
    "trip_id": "11340469:11415072:12153903",
    "route_id": "27-VIC",
    "start_time": "27:02:00",
    "stop_id": "101357",
    "delay": 68,
    "stop_sequence": 1,
    "time": 0
  },
  {
    "trip_id": "11340469:11415072:12153903",
    "route_id": "27-VIC",
    "start_time": "27:02:00",
    "stop_id": "101308",
    "delay": 68,
    "stop_sequence": 2,
    "time": 1769339048
  },
  {
    "trip_id": "11340469:11415072:12153903",
    "route_id": "27-VIC",
    "start_time": "27:02:00",
    "stop_id": "101265",
    "delay": 68,
    "stop_sequence": 3,
    "time": 1769339048
  },
  {
    "trip_id": "11340469:11415072:12153903",
    "route_id": "27-VIC",
    "start_time": "27:02:00",
    "stop_id": "101238",
    "delay": 68,
    "stop_sequence": 4,
    "time": 1769339108
  },
  {
    "trip_id": "11340469:11415072:12153903",
    "route_id": "27-VIC",
    "start_time": "27:02:00",
    "stop_id": "101170",
    "delay": 68,
    "stop_sequence": 5,
    "time": 1769339108
  },
  {
    "trip_id": "11340469:11415072:12153903",
    "route_id": "27-VIC",
    "start_time": "27:02:00",
    "stop_id": "101137",
    "delay": 68,
    "stop_sequence": 6,
    "time": 1769339168
  },
  {
    "trip_id": "11340469:11415072:12153903",
    "route_id": "27-VIC",
    "start_time": "27:02:00",
    "stop_id": "101105",
    "delay": 68,
    "stop_sequence": 7,
    "time": 1769339168
  },
  {
    "trip_id": "11340469:11415072:12153903",
    "route_id": "27-VIC",
    "start_time": "27:02:00",
    "stop_id": "101074",
    "delay": 69,
    "stop_sequence": 8,
    "time": 1769339228
  },
  {
    "trip_id": "11340469:11415072:12153903",
    "route_id": "27-VIC",
    "start_time": "27:02:00",
    "stop_id": "101028",
    "delay": 108,
    "stop_sequence": 9,
    "time": 1769339256
  },
  {
    "trip_id": "11340469:11415072:12153903",
    "route_id": "27-VIC",
    "start_time": "27:02:00",
    "stop_id": "100995",
    "delay": 66,
    "stop_sequence": 10,
    "time": 1769339286
  },
  {
    "trip_id": "11340469:11415072:12153903",
    "route_id": "27-VIC",
    "start_time": "27:02:00",
    "stop_id": "100980",
    "delay": 70,
    "stop_sequence": 11,
    "time": 1769339320
  },
  {
    "trip_id": "11340469:11415072:12153903",
    "route_id": "27-VIC",
    "start_time": "27:02:00",
    "stop_id": "100931",
    "delay": 47,
    "stop_sequence": 12,
    "time": 1769339381
  },
  {
    "trip_id": "11340469:11415072:12153903",
    "route_id": "27-VIC",
    "start_time": "27:02:00",
    "stop_id": "100898",
    "delay": 78,
    "stop_sequence": 13,
    "time": 1769339413
  },
  {
    "trip_id": "11340469:11415072:12153903",
    "route_id": "27-VIC",
    "start_time": "27:02:00",
    "stop_id": "100867",
    "delay": 95,
    "stop_sequence": 14,
    "time": 1769339431
  },
  {
    "trip_id": "11340469:11415072:12153903",
    "route_id": "27-VIC",
    "start_time": "27:02:00",
    "stop_id": "100811",
    "delay": 60,
    "stop_sequence": 15,
    "time": 1769339456
  },
  {
    "trip_id": "11340469:11415072:12153903",
    "route_id": "27-VIC",
    "start_time": "27:02:00",
    "stop_id": "102643",
    "delay": 82,
    "stop_sequence": 16,
    "time": 1769339476
  },
  {
    "trip_id": "11340469:11415072:12153903",
    "route_id": "27-VIC",
    "start_time": "27:02:00",
    "stop_id": "100727",
    "delay": 49,
    "stop_sequence": 17,
    "time": 1769339506
  },
  {
    "trip_id": "11340469:11415072:12153903",
    "route_id": "27-VIC",
    "start_time": "27:02:00",
    "stop_id": "100685",
    "delay": 71,
    "stop_sequence": 18,
    "time": 1769339530
  },
  {
    "trip_id": "11340469:11415072:12153903",
    "route_id": "27-VIC",
    "start_time": "27:02:00",
    "stop_id": "100636",
    "delay": 0,
    "stop_sequence": 19,
    "time": 1769339555
  },
  {
    "trip_id": "11379044:11444986:11463044",
    "route_id": "15-VIC",
    "start_time": "26:27:00",
    "stop_id": "100941",
    "delay": 162,
    "stop_sequence": 15,
    "time": 1769338002
  },
  {
    "trip_id": "11379044:11444986:11463044",
    "route_id": "15-VIC",
    "start_time": "26:27:00",
    "stop_id": "100097",
    "delay": 162,
    "stop_sequence": 16,
    "time": 1769338062
  },
  {
    "trip_id": "11379044:11444986:11463044",
    "route_id": "15-VIC",
    "start_time": "26:27:00",
    "stop_id": "100134",
    "delay": 162,
    "stop_sequence": 17,
    "time": 1769338062
  },
  {
    "trip_id": "11379044:11444986:11463044",
    "route_id": "15-VIC",
    "start_time": "26:27:00",
    "stop_id": "100148",
    "delay": 162,
    "stop_sequence": 18,
    "time": 1769338122
  },
  {
    "trip_id": "11379044:11444986:11463044",
    "route_id": "15-VIC",
    "start_time": "26:27:00",
    "stop_id": "100204",
    "delay": 162,
    "stop_sequence": 19,
    "time": 1769338182
  },
  {
    "trip_id": "11379044:11444986:11463044",
    "route_id": "15-VIC",
    "start_time": "26:27:00",
    "stop_id": "100242",
    "delay": 162,
    "stop_sequence": 20,
    "time": 1769338242
  },
  {
    "trip_id": "11379044:11444986:11463044",
    "route_id": "15-VIC",
    "start_time": "26:27:00",
    "stop_id": "100276",
    "delay": 162,
    "stop_sequence": 21,
    "time": 1769338242
  },
  {
    "trip_id": "11379044:11444986:11463044",
    "route_id": "15-VIC",
    "start_time": "26:27:00",
    "stop_id": "100307",
    "delay": 162,
    "stop_sequence": 22,
    "time": 1769338302
  },
  {
    "trip_id": "11379044:11444986:11463044",
    "route_id": "15-VIC",
    "start_time": "26:27:00",
    "stop_id": "100348",
    "delay": 162,
    "stop_sequence": 23,
    "time": 1769338362
  },
  {
    "trip_id": "11379044:11444986:11463044",
    "route_id": "15-VIC",
    "start_time": "26:27:00",
    "stop_id": "100387",
    "delay": 162,
    "stop_sequence": 24,
    "time": 1769338362
  },
  {
    "trip_id": "11379044:11444986:11463044",
    "route_id": "15-VIC",
    "start_time": "26:27:00",
    "stop_id": "100430",
    "delay": 162,
    "stop_sequence": 25,
    "time": 1769338422
  },
  {
    "trip_id": "11379044:11444986:11463044",
    "route_id": "15-VIC",
    "start_time": "26:27:00",
    "stop_id": "100470",
    "delay": 162,
    "stop_sequence": 26,
    "time": 1769338482
  },
  {
    "trip_id": "11379044:11444986:11463044",
    "route_id": "15-VIC",
    "start_time": "26:27:00",
    "stop_id": "100545",
    "delay": 162,
    "stop_sequence": 27,
    "time": 1769338482
  },
  {
    "trip_id": "11379044:11444986:11463044",
    "route_id": "15-VIC",
    "start_time": "26:27:00",
    "stop_id": "100597",
    "delay": 162,
    "stop_sequence": 28,
    "time": 1769338542
  },
  {
    "trip_id": "11379044:11444986:11463044",
    "route_id": "15-VIC",
    "start_time": "26:27:00",
    "stop_id": "100651",
    "delay": 162,
    "stop_sequence": 29,
    "time": 1769338602
  },
  {
    "trip_id": "11379044:11444986:11463044",
    "route_id": "15-VIC",
    "start_time": "26:27:00",
    "stop_id": "100698",
    "delay": 162,
    "stop_sequence": 30,
    "time": 1769338662
  },
  {
    "trip_id": "11340468:11416053:11464041",
    "route_id": "28-VIC",
    "start_time": "26:43:00",
    "stop_id": "101355",
    "delay": 461,
    "stop_sequence": 1,
    "time": 0
  },
  {
    "trip_id": "11340468:11416053:11464041",
    "route_id": "28-VIC",
    "start_time": "26:43:00",
    "stop_id": "101368",
    "delay": 461,
    "stop_sequence": 2,
    "time": 1769338301
  },
  {
    "trip_id": "11340468:11416053:11464041",
    "route_id": "28-VIC",
    "start_time": "26:43:00",
    "stop_id": "101367",
    "delay": 461,
    "stop_sequence": 3,
    "time": 1769338301
  },
  {
    "trip_id": "11340468:11416053:11464041",
    "route_id": "28-VIC",
    "start_time": "26:43:00",
    "stop_id": "101354",
    "delay": 461,
    "stop_sequence": 4,
    "time": 1769338361
  },
  {
    "trip_id": "11340468:11416053:11464041",
    "route_id": "28-VIC",
    "start_time": "26:43:00",
    "stop_id": "101327",
    "delay": 461,
    "stop_sequence": 5,
    "time": 1769338361
  },
  {
    "trip_id": "11340468:11416053:11464041",
    "route_id": "28-VIC",
    "start_time": "26:43:00",
    "stop_id": "102649",
    "delay": 461,
    "stop_sequence": 6,
    "time": 1769338421
  },
  {
    "trip_id": "11340468:11416053:11464041",
    "route_id": "28-VIC",
    "start_time": "26:43:00",
    "stop_id": "101248",
    "delay": 461,
    "stop_sequence": 7,
    "time": 1769338421
  },
  {
    "trip_id": "11340468:11416053:11464041",
    "route_id": "28-VIC",
    "start_time": "26:43:00",
    "stop_id": "101219",
    "delay": 461,
    "stop_sequence": 8,
    "time": 1769338421
  },
  {
    "trip_id": "11340468:11416053:11464041",
    "route_id": "28-VIC",
    "start_time": "26:43:00",
    "stop_id": "101196",
    "delay": 461,
    "stop_sequence": 9,
    "time": 1769338481
  },
  {
    "trip_id": "11340468:11416053:11464041",
    "route_id": "28-VIC",
    "start_time": "26:43:00",
    "stop_id": "101160",
    "delay": 461,
    "stop_sequence": 10,
    "time": 1769338481
  },
  {
    "trip_id": "11340468:11416053:11464041",
    "route_id": "28-VIC",
    "start_time": "26:43:00",
    "stop_id": "101130",
    "delay": 461,
    "stop_sequence": 11,
    "time": 1769338541
  },
  {
    "trip_id": "11340468:11416053:11464041",
    "route_id": "28-VIC",
    "start_time": "26:43:00",
    "stop_id": "101102",
    "delay": 461,
    "stop_sequence": 12,
    "time": 1769338541
  },
  {
    "trip_id": "11340468:11416053:11464041",
    "route_id": "28-VIC",
    "start_time": "26:43:00",
    "stop_id": "101074",
    "delay": 462,
    "stop_sequence": 13,
    "time": 1769338601
  },
  {
    "trip_id": "11340468:11416053:11464041",
    "route_id": "28-VIC",
    "start_time": "26:43:00",
    "stop_id": "101028",
    "delay": 501,
    "stop_sequence": 14,
    "time": 1769338629
  },
  {
    "trip_id": "11340468:11416053:11464041",
    "route_id": "28-VIC",
    "start_time": "26:43:00",
    "stop_id": "100995",
    "delay": 459,
    "stop_sequence": 15,
    "time": 1769338659
  },
  {
    "trip_id": "11340468:11416053:11464041",
    "route_id": "28-VIC",
    "start_time": "26:43:00",
    "stop_id": "100980",
    "delay": 463,
    "stop_sequence": 16,
    "time": 1769338693
  },
  {
    "trip_id": "11340468:11416053:11464041",
    "route_id": "28-VIC",
    "start_time": "26:43:00",
    "stop_id": "100931",
    "delay": 440,
    "stop_sequence": 17,
    "time": 1769338754
  },
  {
    "trip_id": "11340468:11416053:11464041",
    "route_id": "28-VIC",
    "start_time": "26:43:00",
    "stop_id": "100898",
    "delay": 471,
    "stop_sequence": 18,
    "time": 1769338786
  },
  {
    "trip_id": "11340468:11416053:11464041",
    "route_id": "28-VIC",
    "start_time": "26:43:00",
    "stop_id": "100867",
    "delay": 488,
    "stop_sequence": 19,
    "time": 1769338804
  },
  {
    "trip_id": "11340468:11416053:11464041",
    "route_id": "28-VIC",
    "start_time": "26:43:00",
    "stop_id": "100811",
    "delay": 453,
    "stop_sequence": 20,
    "time": 1769338829
  },
  {
    "trip_id": "11340468:11416053:11464041",
    "route_id": "28-VIC",
    "start_time": "26:43:00",
    "stop_id": "102643",
    "delay": 475,
    "stop_sequence": 21,
    "time": 1769338849
  },
  {
    "trip_id": "11340468:11416053:11464041",
    "route_id": "28-VIC",
    "start_time": "26:43:00",
    "stop_id": "100727",
    "delay": 442,
    "stop_sequence": 22,
    "time": 1769338879
  },
  {
    "trip_id": "11340468:11416053:11464041",
    "route_id": "28-VIC",
    "start_time": "26:43:00",
    "stop_id": "100685",
    "delay": 464,
    "stop_sequence": 23,
    "time": 1769338903
  },
  {
    "trip_id": "11340468:11416053:11464041",
    "route_id": "28-VIC",
    "start_time": "26:43:00",
    "stop_id": "100636",
    "delay": 0,
    "stop_sequence": 24,
    "time": 1769338928
  },
  {
    "trip_id": "11379045:11416052:11463934",
    "route_id": "15-VIC",
    "start_time": "26:28:00",
    "stop_id": "100689",
    "delay": -129,
    "stop_sequence": 26,
    "time": 1769337951
  },
  {
    "trip_id": "11379045:11416052:11463934",
    "route_id": "15-VIC",
    "start_time": "26:28:00",
    "stop_id": "100763",
    "delay": -129,
    "stop_sequence": 27,
    "time": 1769338011
  },
  {
    "trip_id": "11379045:11416052:11463934",
    "route_id": "15-VIC",
    "start_time": "26:28:00",
    "stop_id": "100913",
    "delay": -129,
    "stop_sequence": 28,
    "time": 1769338131
  },
  {
    "trip_id": "11379045:11416052:11463934",
    "route_id": "15-VIC",
    "start_time": "26:28:00",
    "stop_id": "100071",
    "delay": -129,
    "stop_sequence": 29,
    "time": 1769338191
  },
  {
    "trip_id": "11379045:11416052:11463934",
    "route_id": "15-VIC",
    "start_time": "26:28:00",
    "stop_id": "101036",
    "delay": -168,
    "stop_sequence": 30,
    "time": 1769338272
  },
  {
    "trip_id": "11379045:11416052:11463934",
    "route_id": "15-VIC",
    "start_time": "26:28:00",
    "stop_id": "102420",
    "delay": -211,
    "stop_sequence": 31,
    "time": 1769338349
  },
  {
    "trip_id": "11340370:11448765:12153903",
    "route_id": "27-VIC",
    "start_time": "26:32:00",
    "stop_id": "100450",
    "delay": 100,
    "stop_sequence": 15,
    "time": 1769337940
  },
  {
    "trip_id": "11340370:11448765:12153903",
    "route_id": "27-VIC",
    "start_time": "26:32:00",
    "stop_id": "100485",
    "delay": 133,
    "stop_sequence": 16,
    "time": 1769337973
  },
  {
    "trip_id": "11340370:11448765:12153903",
    "route_id": "27-VIC",
    "start_time": "26:32:00",
    "stop_id": "100549",
    "delay": 129,
    "stop_sequence": 17,
    "time": 1769338029
  },
  {
    "trip_id": "11340370:11448765:12153903",
    "route_id": "27-VIC",
    "start_time": "26:32:00",
    "stop_id": "100577",
    "delay": 150,
    "stop_sequence": 18,
    "time": 1769338050
  },
  {
    "trip_id": "11340370:11448765:12153903",
    "route_id": "27-VIC",
    "start_time": "26:32:00",
    "stop_id": "100615",
    "delay": 128,
    "stop_sequence": 19,
    "time": 1769338088
  },
  {
    "trip_id": "11340370:11448765:12153903",
    "route_id": "27-VIC",
    "start_time": "26:32:00",
    "stop_id": "100656",
    "delay": 179,
    "stop_sequence": 20,
    "time": 1769338139
  },
  {
    "trip_id": "11340370:11448765:12153903",
    "route_id": "27-VIC",
    "start_time": "26:32:00",
    "stop_id": "100697",
    "delay": 136,
    "stop_sequence": 21,
    "time": 1769338156
  },
  {
    "trip_id": "11340370:11448765:12153903",
    "route_id": "27-VIC",
    "start_time": "26:32:00",
    "stop_id": "100731",
    "delay": 103,
    "stop_sequence": 22,
    "time": 1769338183
  },
  {
    "trip_id": "11340370:11448765:12153903",
    "route_id": "27-VIC",
    "start_time": "26:32:00",
    "stop_id": "102602",
    "delay": 140,
    "stop_sequence": 23,
    "time": 1769338220
  },
  {
    "trip_id": "11340370:11448765:12153903",
    "route_id": "27-VIC",
    "start_time": "26:32:00",
    "stop_id": "100829",
    "delay": 120,
    "stop_sequence": 24,
    "time": 1769338260
  },
  {
    "trip_id": "11340370:11448765:12153903",
    "route_id": "27-VIC",
    "start_time": "26:32:00",
    "stop_id": "100888",
    "delay": 166,
    "stop_sequence": 25,
    "time": 1769338306
  },
  {
    "trip_id": "11340370:11448765:12153903",
    "route_id": "27-VIC",
    "start_time": "26:32:00",
    "stop_id": "100933",
    "delay": 144,
    "stop_sequence": 26,
    "time": 1769338344
  },
  {
    "trip_id": "11340370:11448765:12153903",
    "route_id": "27-VIC",
    "start_time": "26:32:00",
    "stop_id": "100970",
    "delay": 112,
    "stop_sequence": 27,
    "time": 1769338372
  },
  {
    "trip_id": "11340370:11448765:12153903",
    "route_id": "27-VIC",
    "start_time": "26:32:00",
    "stop_id": "100994",
    "delay": 83,
    "stop_sequence": 28,
    "time": 1769338403
  },
  {
    "trip_id": "11340370:11448765:12153903",
    "route_id": "27-VIC",
    "start_time": "26:32:00",
    "stop_id": "101041",
    "delay": 83,
    "stop_sequence": 29,
    "time": 1769338463
  },
  {
    "trip_id": "11340370:11448765:12153903",
    "route_id": "27-VIC",
    "start_time": "26:32:00",
    "stop_id": "101065",
    "delay": 83,
    "stop_sequence": 30,
    "time": 1769338523
  },
  {
    "trip_id": "11340370:11448765:12153903",
    "route_id": "27-VIC",
    "start_time": "26:32:00",
    "stop_id": "101078",
    "delay": 83,
    "stop_sequence": 31,
    "time": 1769338523
  },
  {
    "trip_id": "11340370:11448765:12153903",
    "route_id": "27-VIC",
    "start_time": "26:32:00",
    "stop_id": "101099",
    "delay": 83,
    "stop_sequence": 32,
    "time": 1769338583
  },
  {
    "trip_id": "11340370:11448765:12153903",
    "route_id": "27-VIC",
    "start_time": "26:32:00",
    "stop_id": "101110",
    "delay": 83,
    "stop_sequence": 33,
    "time": 1769338643
  },
  {
    "trip_id": "11340370:11448765:12153903",
    "route_id": "27-VIC",
    "start_time": "26:32:00",
    "stop_id": "101129",
    "delay": 83,
    "stop_sequence": 34,
    "time": 1769338643
  },
  {
    "trip_id": "11340370:11448765:12153903",
    "route_id": "27-VIC",
    "start_time": "26:32:00",
    "stop_id": "101174",
    "delay": 83,
    "stop_sequence": 35,
    "time": 1769338703
  },
  {
    "trip_id": "11340370:11448765:12153903",
    "route_id": "27-VIC",
    "start_time": "26:32:00",
    "stop_id": "101224",
    "delay": 83,
    "stop_sequence": 36,
    "time": 1769338703
  },
  {
    "trip_id": "11340370:11448765:12153903",
    "route_id": "27-VIC",
    "start_time": "26:32:00",
    "stop_id": "101256",
    "delay": 83,
    "stop_sequence": 37,
    "time": 1769338703
  },
  {
    "trip_id": "11340370:11448765:12153903",
    "route_id": "27-VIC",
    "start_time": "26:32:00",
    "stop_id": "101294",
    "delay": 83,
    "stop_sequence": 38,
    "time": 1769338763
  },
  {
    "trip_id": "11340370:11448765:12153903",
    "route_id": "27-VIC",
    "start_time": "26:32:00",
    "stop_id": "101332",
    "delay": 83,
    "stop_sequence": 39,
    "time": 1769338823
  },
  {
    "trip_id": "11340370:11448765:12153903",
    "route_id": "27-VIC",
    "start_time": "26:32:00",
    "stop_id": "101349",
    "delay": 83,
    "stop_sequence": 40,
    "time": 1769338823
  },
  {
    "trip_id": "11340370:11448765:12153903",
    "route_id": "27-VIC",
    "start_time": "26:32:00",
    "stop_id": "101359",
    "delay": 83,
    "stop_sequence": 41,
    "time": 1769338823
  },
  {
    "trip_id": "11340370:11448765:12153903",
    "route_id": "27-VIC",
    "start_time": "26:32:00",
    "stop_id": "101390",
    "delay": 83,
    "stop_sequence": 42,
    "time": 1769338883
  },
  {
    "trip_id": "11340370:11448765:12153903",
    "route_id": "27-VIC",
    "start_time": "26:32:00",
    "stop_id": "101422",
    "delay": 83,
    "stop_sequence": 43,
    "time": 1769338883
  },
  {
    "trip_id": "11340370:11448765:12153903",
    "route_id": "27-VIC",
    "start_time": "26:32:00",
    "stop_id": "101431",
    "delay": 83,
    "stop_sequence": 44,
    "time": 1769338883
  },
  {
    "trip_id": "11340370:11448765:12153903",
    "route_id": "27-VIC",
    "start_time": "26:32:00",
    "stop_id": "101426",
    "delay": 83,
    "stop_sequence": 45,
    "time": 1769338943
  },
  {
    "trip_id": "11340370:11448765:12153903",
    "route_id": "27-VIC",
    "start_time": "26:32:00",
    "stop_id": "101420",
    "delay": 83,
    "stop_sequence": 46,
    "time": 1769338943
  },
  {
    "trip_id": "11340370:11448765:12153903",
    "route_id": "27-VIC",
    "start_time": "26:32:00",
    "stop_id": "101405",
    "delay": 83,
    "stop_sequence": 47,
    "time": 1769339003
  },
  {
    "trip_id": "11340370:11448765:12153903",
    "route_id": "27-VIC",
    "start_time": "26:32:00",
    "stop_id": "101357",
    "delay": 83,
    "stop_sequence": 48,
    "time": 1769339003
  },
  {
    "trip_id": "11340369:11423304:11464041",
    "route_id": "28-VIC",
    "start_time": "26:17:00",
    "stop_id": "101077",
    "delay": 469,
    "stop_sequence": 30,
    "time": 1769337949
  },
  {
    "trip_id": "11340369:11423304:11464041",
    "route_id": "28-VIC",
    "start_time": "26:17:00",
    "stop_id": "101108",
    "delay": 469,
    "stop_sequence": 31,
    "time": 1769338009
  },
  {
    "trip_id": "11340369:11423304:11464041",
    "route_id": "28-VIC",
    "start_time": "26:17:00",
    "stop_id": "101123",
    "delay": 469,
    "stop_sequence": 32,
    "time": 1769338069
  },
  {
    "trip_id": "11340369:11423304:11464041",
    "route_id": "28-VIC",
    "start_time": "26:17:00",
    "stop_id": "101149",
    "delay": 469,
    "stop_sequence": 33,
    "time": 1769338069
  },
  {
    "trip_id": "11340369:11423304:11464041",
    "route_id": "28-VIC",
    "start_time": "26:17:00",
    "stop_id": "101220",
    "delay": 469,
    "stop_sequence": 34,
    "time": 1769338129
  },
  {
    "trip_id": "11340369:11423304:11464041",
    "route_id": "28-VIC",
    "start_time": "26:17:00",
    "stop_id": "101236",
    "delay": 469,
    "stop_sequence": 35,
    "time": 1769338129
  },
  {
    "trip_id": "11340369:11423304:11464041",
    "route_id": "28-VIC",
    "start_time": "26:17:00",
    "stop_id": "101274",
    "delay": 469,
    "stop_sequence": 36,
    "time": 1769338189
  },
  {
    "trip_id": "11340369:11423304:11464041",
    "route_id": "28-VIC",
    "start_time": "26:17:00",
    "stop_id": "101305",
    "delay": 469,
    "stop_sequence": 37,
    "time": 1769338189
  },
  {
    "trip_id": "11340369:11423304:11464041",
    "route_id": "28-VIC",
    "start_time": "26:17:00",
    "stop_id": "101355",
    "delay": 469,
    "stop_sequence": 38,
    "time": 1769338249
  },
  {
    "trip_id": "11374191:11417892:11459982",
    "route_id": "95-VIC",
    "start_time": "26:32:00",
    "stop_id": "100456",
    "delay": 151,
    "stop_sequence": 8,
    "time": 1769337991
  },
  {
    "trip_id": "11374191:11417892:11459982",
    "route_id": "95-VIC",
    "start_time": "26:32:00",
    "stop_id": "100554",
    "delay": 151,
    "stop_sequence": 9,
    "time": 1769338051
  },
  {
    "trip_id": "11374191:11417892:11459982",
    "route_id": "95-VIC",
    "start_time": "26:32:00",
    "stop_id": "100709",
    "delay": 151,
    "stop_sequence": 10,
    "time": 1769338171
  },
  {
    "trip_id": "11374191:11417892:11459982",
    "route_id": "95-VIC",
    "start_time": "26:32:00",
    "stop_id": "100817",
    "delay": 151,
    "stop_sequence": 11,
    "time": 1769338231
  },
  {
    "trip_id": "11374191:11417892:11459982",
    "route_id": "95-VIC",
    "start_time": "26:32:00",
    "stop_id": "101063",
    "delay": 151,
    "stop_sequence": 12,
    "time": 1769338411
  },
  {
    "trip_id": "11374191:11417892:11459982",
    "route_id": "95-VIC",
    "start_time": "26:32:00",
    "stop_id": "101254",
    "delay": 151,
    "stop_sequence": 13,
    "time": 1769338591
  },
  {
    "trip_id": "11374191:11417892:11459982",
    "route_id": "95-VIC",
    "start_time": "26:32:00",
    "stop_id": "101260",
    "delay": 151,
    "stop_sequence": 14,
    "time": 1769338711
  },
  {
    "trip_id": "11374191:11417892:11459982",
    "route_id": "95-VIC",
    "start_time": "26:32:00",
    "stop_id": "101245",
    "delay": 151,
    "stop_sequence": 15,
    "time": 1769338771
  },
  {
    "trip_id": "11374191:11417892:11459982",
    "route_id": "95-VIC",
    "start_time": "26:32:00",
    "stop_id": "101275",
    "delay": 151,
    "stop_sequence": 16,
    "time": 1769338831
  },
  {
    "trip_id": "11374191:11417892:11459982",
    "route_id": "95-VIC",
    "start_time": "26:32:00",
    "stop_id": "101326",
    "delay": 151,
    "stop_sequence": 17,
    "time": 1769338831
  },
  {
    "trip_id": "11374191:11417892:11459982",
    "route_id": "95-VIC",
    "start_time": "26:32:00",
    "stop_id": "101380",
    "delay": 151,
    "stop_sequence": 18,
    "time": 1769338891
  },
  {
    "trip_id": "11374191:11417892:11459982",
    "route_id": "95-VIC",
    "start_time": "26:32:00",
    "stop_id": "101467",
    "delay": 151,
    "stop_sequence": 19,
    "time": 1769338951
  },
  {
    "trip_id": "11374191:11417892:11459982",
    "route_id": "95-VIC",
    "start_time": "26:32:00",
    "stop_id": "101513",
    "delay": 151,
    "stop_sequence": 20,
    "time": 1769339011
  },
  {
    "trip_id": "11374191:11417892:11459982",
    "route_id": "95-VIC",
    "start_time": "26:32:00",
    "stop_id": "101546",
    "delay": 151,
    "stop_sequence": 21,
    "time": 1769339071
  },
  {
    "trip_id": "11374191:11417892:11459982",
    "route_id": "95-VIC",
    "start_time": "26:32:00",
    "stop_id": "101597",
    "delay": 151,
    "stop_sequence": 22,
    "time": 1769339191
  },
  {
    "trip_id": "11374191:11417892:11459982",
    "route_id": "95-VIC",
    "start_time": "26:32:00",
    "stop_id": "101632",
    "delay": 151,
    "stop_sequence": 23,
    "time": 1769339311
  },
  {
    "trip_id": "11374191:11417892:11459982",
    "route_id": "95-VIC",
    "start_time": "26:32:00",
    "stop_id": "102442",
    "delay": 151,
    "stop_sequence": 24,
    "time": 1769339371
  },
  {
    "trip_id": "11374191:11417892:11459982",
    "route_id": "95-VIC",
    "start_time": "26:32:00",
    "stop_id": "101542",
    "delay": 151,
    "stop_sequence": 25,
    "time": 1769339491
  },
  {
    "trip_id": "11277554:11419413:11461277",
    "route_id": "4-VIC",
    "start_time": "26:43:00",
    "stop_id": "100076",
    "delay": -21,
    "stop_sequence": 3,
    "time": 1769337999
  },
  {
    "trip_id": "11277554:11419413:11461277",
    "route_id": "4-VIC",
    "start_time": "26:43:00",
    "stop_id": "100394",
    "delay": -21,
    "stop_sequence": 4,
    "time": 1769337999
  },
  {
    "trip_id": "11277554:11419413:11461277",
    "route_id": "4-VIC",
    "start_time": "26:43:00",
    "stop_id": "100146",
    "delay": -21,
    "stop_sequence": 5,
    "time": 1769338059
  },
  {
    "trip_id": "11277554:11419413:11461277",
    "route_id": "4-VIC",
    "start_time": "26:43:00",
    "stop_id": "100178",
    "delay": -21,
    "stop_sequence": 6,
    "time": 1769338119
  },
  {
    "trip_id": "11277554:11419413:11461277",
    "route_id": "4-VIC",
    "start_time": "26:43:00",
    "stop_id": "100198",
    "delay": -21,
    "stop_sequence": 7,
    "time": 1769338179
  },
  {
    "trip_id": "11277554:11419413:11461277",
    "route_id": "4-VIC",
    "start_time": "26:43:00",
    "stop_id": "102012",
    "delay": 0,
    "stop_sequence": 8,
    "time": 1769338260
  },
  {
    "trip_id": "11277554:11419413:11461277",
    "route_id": "4-VIC",
    "start_time": "26:43:00",
    "stop_id": "100237",
    "delay": 0,
    "stop_sequence": 9,
    "time": 1769338320
  },
  {
    "trip_id": "11277554:11419413:11461277",
    "route_id": "4-VIC",
    "start_time": "26:43:00",
    "stop_id": "100266",
    "delay": 0,
    "stop_sequence": 10,
    "time": 1769338380
  },
  {
    "trip_id": "11277554:11419413:11461277",
    "route_id": "4-VIC",
    "start_time": "26:43:00",
    "stop_id": "100280",
    "delay": 0,
    "stop_sequence": 11,
    "time": 1769338380
  },
  {
    "trip_id": "11277554:11419413:11461277",
    "route_id": "4-VIC",
    "start_time": "26:43:00",
    "stop_id": "100301",
    "delay": 0,
    "stop_sequence": 12,
    "time": 1769338440
  },
  {
    "trip_id": "11277554:11419413:11461277",
    "route_id": "4-VIC",
    "start_time": "26:43:00",
    "stop_id": "100322",
    "delay": 0,
    "stop_sequence": 13,
    "time": 1769338440
  },
  {
    "trip_id": "11277554:11419413:11461277",
    "route_id": "4-VIC",
    "start_time": "26:43:00",
    "stop_id": "100337",
    "delay": 0,
    "stop_sequence": 14,
    "time": 1769338440
  },
  {
    "trip_id": "11277554:11419413:11461277",
    "route_id": "4-VIC",
    "start_time": "26:43:00",
    "stop_id": "100385",
    "delay": 0,
    "stop_sequence": 15,
    "time": 1769338500
  },
  {
    "trip_id": "11277554:11419413:11461277",
    "route_id": "4-VIC",
    "start_time": "26:43:00",
    "stop_id": "100442",
    "delay": 0,
    "stop_sequence": 16,
    "time": 1769338500
  },
  {
    "trip_id": "11277554:11419413:11461277",
    "route_id": "4-VIC",
    "start_time": "26:43:00",
    "stop_id": "100514",
    "delay": 0,
    "stop_sequence": 17,
    "time": 1769338560
  },
  {
    "trip_id": "11277554:11419413:11461277",
    "route_id": "4-VIC",
    "start_time": "26:43:00",
    "stop_id": "100566",
    "delay": 0,
    "stop_sequence": 18,
    "time": 1769338620
  },
  {
    "trip_id": "11277554:11419413:11461277",
    "route_id": "4-VIC",
    "start_time": "26:43:00",
    "stop_id": "100618",
    "delay": 0,
    "stop_sequence": 19,
    "time": 1769338620
  },
  {
    "trip_id": "11277554:11419413:11461277",
    "route_id": "4-VIC",
    "start_time": "26:43:00",
    "stop_id": "100653",
    "delay": 0,
    "stop_sequence": 20,
    "time": 1769338680
  },
  {
    "trip_id": "11277554:11419413:11461277",
    "route_id": "4-VIC",
    "start_time": "26:43:00",
    "stop_id": "100763",
    "delay": 0,
    "stop_sequence": 21,
    "time": 1769338740
  },
  {
    "trip_id": "11277554:11419413:11461277",
    "route_id": "4-VIC",
    "start_time": "26:43:00",
    "stop_id": "100827",
    "delay": 0,
    "stop_sequence": 22,
    "time": 1769338740
  },
  {
    "trip_id": "11277554:11419413:11461277",
    "route_id": "4-VIC",
    "start_time": "26:43:00",
    "stop_id": "100864",
    "delay": 0,
    "stop_sequence": 23,
    "time": 1769338740
  },
  {
    "trip_id": "11277554:11419413:11461277",
    "route_id": "4-VIC",
    "start_time": "26:43:00",
    "stop_id": "100913",
    "delay": 0,
    "stop_sequence": 24,
    "time": 1769338800
  },
  {
    "trip_id": "11277554:11419413:11461277",
    "route_id": "4-VIC",
    "start_time": "26:43:00",
    "stop_id": "100937",
    "delay": 0,
    "stop_sequence": 25,
    "time": 1769338800
  },
  {
    "trip_id": "11277554:11419413:11461277",
    "route_id": "4-VIC",
    "start_time": "26:43:00",
    "stop_id": "100951",
    "delay": 0,
    "stop_sequence": 26,
    "time": 1769338800
  },
  {
    "trip_id": "11277554:11419413:11461277",
    "route_id": "4-VIC",
    "start_time": "26:43:00",
    "stop_id": "100071",
    "delay": 0,
    "stop_sequence": 27,
    "time": 1769338860
  },
  {
    "trip_id": "11277554:11419413:11461277",
    "route_id": "4-VIC",
    "start_time": "26:43:00",
    "stop_id": "101036",
    "delay": 21,
    "stop_sequence": 28,
    "time": 1769338941
  },
  {
    "trip_id": "11277554:11419413:11461277",
    "route_id": "4-VIC",
    "start_time": "26:43:00",
    "stop_id": "102420",
    "delay": -22,
    "stop_sequence": 29,
    "time": 1769339018
  }
]